{
    "direction_driving": {
        "gt": 0,
        "choices": [
            [
                "left",
                "right",
                "left",
                "left",
                "right",
                "left"
            ],
            [
                "right",
                "right",
                "left",
                "left",
                "left",
                "right"
            ],
            [
                "right",
                "left",
                "left",
                "right",
                "right",
                "right"
            ],
            [
                "left",
                "right",
                "right",
                "right",
                "right",
                "right"
            ]
        ]
    },
    "direction_walking": {
        "gt": 1,
        "choices": [
            [
                "left",
                "right",
                "right",
                "right",
                "left",
                "left"
            ],
            [
                "left",
                "right",
                "right",
                "left",
                "right",
                "right"
            ],
            [
                "right",
                "left",
                "right",
                "left",
                "right",
                "right"
            ],
            [
                "right",
                "right",
                "right",
                "left",
                "left",
                "right"
            ]
        ]
    },
    "distance_driving": {
        "gt": 1,
        "choices": [
            [
                "513.0 ft",
                "0.1 mi",
                "424.2 ft",
                "0.3 mi",
                "436.2 ft",
                "192.8 ft"
            ],
            [
                "449 ft",
                "0.3 mi",
                "400 ft",
                "98 ft",
                "0.1 mi",
                "0.1 mi"
            ],
            [
                "299.6 ft",
                "0.3 mi",
                "562.7 ft",
                "0.1 mi",
                "152.0 ft",
                "299.4 ft"
            ],
            [
                "537.8 ft",
                "0.2 mi",
                "600.7 ft",
                "0.4 mi",
                "208.8 ft",
                "432.6 ft"
            ]
        ]
    },
    "distance_walking": {
        "gt": 2,
        "choices": [
            [
                "0.3 mi",
                "183.2 ft",
                "0.4 mi",
                "255.9 ft",
                "209.3 ft",
                "0.4 mi"
            ],
            [
                "0.3 mi",
                "30.5 ft",
                "0.2 mi",
                "194.3 ft",
                "141.0 ft",
                "0.3 mi"
            ],
            [
                "203 ft",
                "0.3 mi",
                "0.1 mi",
                "98 ft",
                "0.1 mi",
                "0.1 mi"
            ],
            [
                "0.4 mi",
                "232.3 ft",
                "0.4 mi",
                "275.0 ft",
                "202.3 ft",
                "0.3 mi"
            ]
        ]
    },
    "optimal_route": {
        "gt": 0,
        "choices": [
            [
                "Chase Bank, 156 2nd Ave, New York, NY 10003",
                "Blink Fitness East Village, 98 Avenue A, New York, NY 10009",
                "Lower East Side People's FCU, 37 Avenue B, New York, NY 10009"
            ],
            [
                "Blink Fitness East Village, 98 Avenue A, New York, NY 10009",
                "Chase Bank, 156 2nd Ave, New York, NY 10003",
                "Lower East Side People's FCU, 37 Avenue B, New York, NY 10009"
            ],
            [
                "Lower East Side People's FCU, 37 Avenue B, New York, NY 10009",
                "Blink Fitness East Village, 98 Avenue A, New York, NY 10009",
                "Chase Bank, 156 2nd Ave, New York, NY 10003"
            ],
            [
                "Lower East Side People's FCU, 37 Avenue B, New York, NY 10009",
                "Chase Bank, 156 2nd Ave, New York, NY 10003",
                "Blink Fitness East Village, 98 Avenue A, New York, NY 10009"
            ]
        ]
    }
}